[
  {
    "id": 3600949,
    "name": "Tegucigalpa",
    "lat": 14.0818,
    "lng": -87.20681
  },
  {
    "id": 3601782,
    "name": "San Pedro Sula",
    "lat": 15.50585,
    "lng": -88.02588
  },
  {
    "id": 3608248,
    "name": "La Ceiba",
    "lat": 15.75971,
    "lng": -86.78221
  },
  {
    "id": 3613533,
    "name": "Choloma",
    "lat": 15.61444,
    "lng": -87.95302
  },
  {
    "id": 3610613,
    "name": "El Progreso",
    "lat": 15.4,
    "lng": -87.8
  },
  {
    "id": 3613528,
    "name": "Ciudad Choluteca",
    "lat": 13.30569,
    "lng": -87.17882
  },
  {
    "id": 3613321,
    "name": "Comayagua",
    "lat": 14.45577,
    "lng": -87.63968
  },
  {
    "id": 3600026,
    "name": "Puerto Cortez",
    "lat": 15.82562,
    "lng": -87.92968
  },
  {
    "id": 3607511,
    "name": "La Lima",
    "lat": 15.43333,
    "lng": -87.91667
  },
  {
    "id": 3612907,
    "name": "Danlí",
    "lat": 14.03333,
    "lng": -86.58333
  },
  {
    "id": 3601311,
    "name": "Siguatepeque",
    "lat": 14.59691,
    "lng": -87.83102
  },
  {
    "id": 3608503,
    "name": "Juticalpa",
    "lat": 14.66438,
    "lng": -86.22246
  },
  {
    "id": 3600327,
    "name": "Villanueva",
    "lat": 15.31476,
    "lng": -87.99383
  },
  {
    "id": 3600704,
    "name": "Tocoa",
    "lat": 15.68333,
    "lng": -86.0
  },
  {
    "id": 3600931,
    "name": "Tela",
    "lat": 15.77425,
    "lng": -87.46731
  },
  {
    "id": 3601494,
    "name": "Santa Rosa de Copán",
    "lat": 14.77388,
    "lng": -88.7756
  },
  {
    "id": 3604251,
    "name": "Olanchito",
    "lat": 15.48131,
    "lng": -86.57415
  },
  {
    "id": 3601977,
    "name": "San Lorenzo",
    "lat": 13.42417,
    "lng": -87.44722
  },
  {
    "id": 3613394,
    "name": "Cofradía",
    "lat": 15.4,
    "lng": -88.15
  },
  {
    "id": 3610965,
    "name": "El Paraíso",
    "lat": 13.86667,
    "lng": -86.55
  },
  {
    "id": 3607254,
    "name": "La Paz",
    "lat": 14.32124,
    "lng": -87.67589
  },
  {
    "id": 3600195,
    "name": "Yoro",
    "lat": 15.13824,
    "lng": -87.12838
  },
  {
    "id": 3603330,
    "name": "Potrerillos",
    "lat": 15.23008,
    "lng": -87.96386
  },
  {
    "id": 3601691,
    "name": "Santa Bárbara",
    "lat": 14.92217,
    "lng": -88.23756
  },
  {
    "id": 3607986,
    "name": "La Entrada",
    "lat": 15.06381,
    "lng": -88.74627
  },
  {
    "id": 3604522,
    "name": "Nacaome",
    "lat": 13.53917,
    "lng": -87.48913
  },
  {
    "id": 3608834,
    "name": "Intibucá",
    "lat": 14.31226,
    "lng": -88.17608
  },
  {
    "id": 3601072,
    "name": "Talanga",
    "lat": 14.4,
    "lng": -87.08333
  },
  {
    "id": 3609418,
    "name": "Guaimaca",
    "lat": 14.53333,
    "lng": -86.81667
  },
  {
    "id": 3601517,
    "name": "Santa Rita",
    "lat": 15.16667,
    "lng": -87.28333
  },
  {
    "id": 3604584,
    "name": "Morazán",
    "lat": 15.31667,
    "lng": -87.6
  },
  {
    "id": 3601627,
    "name": "Santa Cruz de Yojoa",
    "lat": 14.98086,
    "lng": -87.89091
  },
  {
    "id": 3605005,
    "name": "Marcala",
    "lat": 14.15661,
    "lng": -88.03466
  },
  {
    "id": 3601403,
    "name": "Sabá",
    "lat": 15.46667,
    "lng": -86.25
  },
  {
    "id": 3600591,
    "name": "Trujillo",
    "lat": 15.91741,
    "lng": -85.95263
  },
  {
    "id": 3611150,
    "name": "El Negrito",
    "lat": 15.31667,
    "lng": -87.7
  },
  {
    "id": 3614872,
    "name": "Baracoa",
    "lat": 15.77581,
    "lng": -87.85255
  },
  {
    "id": 3601888,
    "name": "San Marcos de Colón",
    "lat": 13.43333,
    "lng": -86.8
  },
  {
    "id": 3604384,
    "name": "Nueva Ocotepeque",
    "lat": 14.43382,
    "lng": -89.18281
  },
  {
    "id": 3603649,
    "name": "Pimienta Vieja",
    "lat": 15.23333,
    "lng": -87.96667
  },
  {
    "id": 3609586,
    "name": "Gracias",
    "lat": 14.59065,
    "lng": -88.58612
  },
  {
    "id": 3615509,
    "name": "Agua Blanca Sur",
    "lat": 15.25,
    "lng": -87.88333
  },
  {
    "id": 3602736,
    "name": "Coxen Hole",
    "lat": 16.31553,
    "lng": -86.53966
  },
  {
    "id": 3606251,
    "name": "Las Vegas, Santa Barbara",
    "lat": 14.87649,
    "lng": -88.07473
  },
  {
    "id": 3610060,
    "name": "El Triunfo",
    "lat": 13.11667,
    "lng": -87.0
  },
  {
    "id": 3608715,
    "name": "Jesús de Otoro",
    "lat": 14.48775,
    "lng": -87.98181
  },
  {
    "id": 3615250,
    "name": "La Alianza",
    "lat": 13.51222,
    "lng": -87.72444
  },
  {
    "id": 3604686,
    "name": "Monjarás",
    "lat": 13.20056,
    "lng": -87.37417
  },
  {
    "id": 3614319,
    "name": "Campamento",
    "lat": 14.55,
    "lng": -86.65
  },
  {
    "id": 3601921,
    "name": "San Manuel",
    "lat": 15.33143,
    "lng": -87.92115
  },
  {
    "id": 3613230,
    "name": "Copán Ruinas",
    "lat": 14.83936,
    "lng": -89.15583
  },
  {
    "id": 3604835,
    "name": "Mezapa",
    "lat": 15.58333,
    "lng": -87.65
  },
  {
    "id": 3606292,
    "name": "Las Trojes",
    "lat": 14.06667,
    "lng": -85.98333
  },
  {
    "id": 3614970,
    "name": "Azacualpa",
    "lat": 15.34364,
    "lng": -88.55226
  },
  {
    "id": 3600338,
    "name": "Villa de San Francisco",
    "lat": 14.16667,
    "lng": -86.96667
  },
  {
    "id": 3601984,
    "name": "San Juan Pueblo",
    "lat": 15.58333,
    "lng": -87.23333
  },
  {
    "id": 3601932,
    "name": "San Luis",
    "lat": 15.12692,
    "lng": -88.43931
  },
  {
    "id": 3609293,
    "name": "Guanaja",
    "lat": 16.44186,
    "lng": -85.88717
  },
  {
    "id": 3602281,
    "name": "San Francisco de la Paz",
    "lat": 14.9,
    "lng": -86.2
  },
  {
    "id": 3600340,
    "name": "Villa de San Antonio",
    "lat": 14.32594,
    "lng": -87.61351
  },
  {
    "id": 3615279,
    "name": "Ajuterique",
    "lat": 14.38304,
    "lng": -87.70965
  },
  {
    "id": 3601903,
    "name": "San Marcos",
    "lat": 14.40788,
    "lng": -88.95525
  },
  {
    "id": 3609681,
    "name": "Florida",
    "lat": 15.02692,
    "lng": -88.83567
  },
  {
    "id": 3607966,
    "name": "La Esperanza",
    "lat": 14.30158,
    "lng": -88.16725
  },
  {
    "id": 3612929,
    "name": "Cuyamel",
    "lat": 15.66505,
    "lng": -88.19478
  },
  {
    "id": 3603157,
    "name": "Puerto Lempira",
    "lat": 15.26566,
    "lng": -83.77436
  },
  {
    "id": 3602444,
    "name": "San Antonio de Cortés",
    "lat": 15.11611,
    "lng": -88.04074
  },
  {
    "id": 3604229,
    "name": "Omoa",
    "lat": 15.77603,
    "lng": -88.03833
  },
  {
    "id": 3613171,
    "name": "Corquín",
    "lat": 14.56667,
    "lng": -88.86667
  },
  {
    "id": 3607540,
    "name": "La Libertad",
    "lat": 14.75792,
    "lng": -87.60759
  },
  {
    "id": 3600966,
    "name": "Taulabé",
    "lat": 14.69251,
    "lng": -87.96537
  },
  {
    "id": 3600422,
    "name": "Valle de Ángeles",
    "lat": 14.1578,
    "lng": -87.04263
  },
  {
    "id": 3601543,
    "name": "Santa María del Real",
    "lat": 14.76667,
    "lng": -85.95
  },
  {
    "id": 3615069,
    "name": "Arizona",
    "lat": 15.63333,
    "lng": -87.31667
  },
  {
    "id": 3600608,
    "name": "Trinidad",
    "lat": 15.14237,
    "lng": -88.23321
  },
  {
    "id": 3600841,
    "name": "Teupasenti",
    "lat": 14.21667,
    "lng": -86.7
  },
  {
    "id": 3607647,
    "name": "La Jutosa",
    "lat": 15.64166,
    "lng": -87.99201
  },
  {
    "id": 3600629,
    "name": "Tras Cerros",
    "lat": 15.3,
    "lng": -88.66667
  },
  {
    "id": 3614663,
    "name": "Brus Laguna",
    "lat": 15.75,
    "lng": -84.48333
  },
  {
    "id": 3607419,
    "name": "La Masica",
    "lat": 15.61667,
    "lng": -87.11667
  },
  {
    "id": 3602097,
    "name": "San José de Colinas",
    "lat": 15.04101,
    "lng": -88.30186
  },
  {
    "id": 3604518,
    "name": "Naco",
    "lat": 15.39106,
    "lng": -88.18312
  },
  {
    "id": 3601899,
    "name": "San Marcos",
    "lat": 15.30248,
    "lng": -88.41605
  },
  {
    "id": 3600139,
    "name": "Zambrano",
    "lat": 14.26667,
    "lng": -87.4
  },
  {
    "id": 3606069,
    "name": "Lejamaní",
    "lat": 14.36681,
    "lng": -87.7072
  },
  {
    "id": 3604478,
    "name": "Naranjito",
    "lat": 14.95297,
    "lng": -88.68333
  },
  {
    "id": 3603627,
    "name": "Pinalejo",
    "lat": 15.38705,
    "lng": -88.39207
  },
  {
    "id": 3614705,
    "name": "Bonito Oriental",
    "lat": 15.74765,
    "lng": -85.73559
  },
  {
    "id": 3607294,
    "name": "Langue",
    "lat": 13.62083,
    "lng": -87.6525
  },
  {
    "id": 3601999,
    "name": "San Juan de Flores",
    "lat": 14.26667,
    "lng": -87.03333
  },
  {
    "id": 3609389,
    "name": "Gualaco",
    "lat": 15.02521,
    "lng": -86.07076
  },
  {
    "id": 3612813,
    "name": "Dulce Nombre",
    "lat": 14.84802,
    "lng": -88.8316
  },
  {
    "id": 3608500,
    "name": "Jutiquile",
    "lat": 14.71667,
    "lng": -86.08333
  },
  {
    "id": 3601707,
    "name": "Santa Ana",
    "lat": 15.65,
    "lng": -87.06667
  },
  {
    "id": 3603221,
    "name": "Pueblo Nuevo",
    "lat": 15.34655,
    "lng": -87.99041
  },
  {
    "id": 3604795,
    "name": "Minas de Oro",
    "lat": 14.79611,
    "lng": -87.34654
  },
  {
    "id": 3603856,
    "name": "Peña Blanca",
    "lat": 15.53333,
    "lng": -88.05
  },
  {
    "id": 3601834,
    "name": "San Nicolás",
    "lat": 14.9423,
    "lng": -88.32796
  },
  {
    "id": 3602952,
    "name": "Quimistán",
    "lat": 15.34752,
    "lng": -88.4052
  },
  {
    "id": 3602758,
    "name": "Río Lindo",
    "lat": 15.0462,
    "lng": -87.98632
  },
  {
    "id": 3602355,
    "name": "San Esteban",
    "lat": 15.21231,
    "lng": -85.76996
  },
  {
    "id": 3615391,
    "name": "Agua Fría",
    "lat": 13.46889,
    "lng": -87.55111
  },
  {
    "id": 3603805,
    "name": "Pespire",
    "lat": 13.59222,
    "lng": -87.36167
  },
  {
    "id": 3610693,
    "name": "El Porvenir",
    "lat": 13.76167,
    "lng": -87.34583
  },
  {
    "id": 3606048,
    "name": "Lepaera",
    "lat": 14.77876,
    "lng": -88.5902
  },
  {
    "id": 3611572,
    "name": "Elíxir",
    "lat": 15.48333,
    "lng": -86.3
  },
  {
    "id": 3600232,
    "name": "Yarumela",
    "lat": 14.33578,
    "lng": -87.64557
  },
  {
    "id": 3606171,
    "name": "La Unión",
    "lat": 14.81387,
    "lng": -88.40845
  },
  {
    "id": 3614012,
    "name": "Casa Quemada",
    "lat": 15.11667,
    "lng": -88.08333
  },
  {
    "id": 3609690,
    "name": "Flores",
    "lat": 14.29442,
    "lng": -87.57142
  },
  {
    "id": 3606669,
    "name": "Las Lajas",
    "lat": 14.78333,
    "lng": -87.75
  },
  {
    "id": 3610813,
    "name": "El Pino",
    "lat": 15.7,
    "lng": -86.93333
  },
  {
    "id": 3600134,
    "name": "Zamora",
    "lat": 15.63333,
    "lng": -86.06667
  },
  {
    "id": 3615065,
    "name": "Armenta",
    "lat": 15.5,
    "lng": -88.05
  },
  {
    "id": 3604579,
    "name": "Morocelí",
    "lat": 14.11667,
    "lng": -86.86667
  },
  {
    "id": 3612064,
    "name": "El Ciruelo",
    "lat": 15.29443,
    "lng": -88.5083
  },
  {
    "id": 3610675,
    "name": "El Porvenir",
    "lat": 15.83333,
    "lng": -87.93333
  },
  {
    "id": 3613015,
    "name": "Cucuyagua",
    "lat": 14.64777,
    "lng": -88.87385
  },
  {
    "id": 3615125,
    "name": "Arada",
    "lat": 14.84582,
    "lng": -88.30108
  },
  {
    "id": 3600357,
    "name": "Victoria",
    "lat": 15.50381,
    "lng": -87.82625
  },
  {
    "id": 3613189,
    "name": "Corocito",
    "lat": 15.75,
    "lng": -85.78333
  },
  {
    "id": 3602603,
    "name": "Salamá",
    "lat": 14.83333,
    "lng": -86.58333
  },
  {
    "id": 3608514,
    "name": "Jutiapa",
    "lat": 15.76667,
    "lng": -86.51667
  },
  {
    "id": 3602301,
    "name": "San Francisco",
    "lat": 15.65,
    "lng": -87.05
  },
  {
    "id": 3604270,
    "name": "Ojojona",
    "lat": 13.93389,
    "lng": -87.29583
  },
  {
    "id": 3601159,
    "name": "Sulaco",
    "lat": 14.91667,
    "lng": -87.26667
  },
  {
    "id": 3614835,
    "name": "Barra Patuca",
    "lat": 15.8,
    "lng": -84.28333
  },
  {
    "id": 3603097,
    "name": "Quebrada de Arena",
    "lat": 15.76667,
    "lng": -85.91667
  },
  {
    "id": 3609112,
    "name": "Güinope",
    "lat": 13.88333,
    "lng": -86.93333
  },
  {
    "id": 3601519,
    "name": "Santa Rita, Copan",
    "lat": 14.86748,
    "lng": -89.1
  },
  {
    "id": 3609667,
    "name": "French Harbor",
    "lat": 16.35,
    "lng": -86.43333
  },
  {
    "id": 3607381,
    "name": "La Mina",
    "lat": 15.31667,
    "lng": -87.83333
  },
  {
    "id": 3601039,
    "name": "Támara",
    "lat": 14.16913,
    "lng": -87.34067
  },
  {
    "id": 3608798,
    "name": "Jacaleapa",
    "lat": 14.01667,
    "lng": -86.66667
  },
  {
    "id": 3610377,
    "name": "El Rosario",
    "lat": 14.8,
    "lng": -87.76667
  },
  {
    "id": 3602561,
    "name": "Sambo Creek",
    "lat": 15.81667,
    "lng": -86.68333
  },
  {
    "id": 3600642,
    "name": "Toyós",
    "lat": 15.55,
    "lng": -87.65
  },
  {
    "id": 3607847,
    "name": "La Guacamaya",
    "lat": 15.25,
    "lng": -87.8
  },
  {
    "id": 3609928,
    "name": "El Zapotal del Norte",
    "lat": 15.51667,
    "lng": -88.05
  },
  {
    "id": 3601162,
    "name": "Sula",
    "lat": 15.24765,
    "lng": -88.56047
  },
  {
    "id": 3607983,
    "name": "La Ermita",
    "lat": 14.46667,
    "lng": -87.06667
  },
  {
    "id": 3611144,
    "name": "El Níspero",
    "lat": 14.76667,
    "lng": -88.33333
  },
  {
    "id": 3602786,
    "name": "Río Blanquito",
    "lat": 15.72756,
    "lng": -87.90151
  },
  {
    "id": 3601462,
    "name": "Santiago de Puringla",
    "lat": 14.35783,
    "lng": -87.9041
  },
  {
    "id": 3601436,
    "name": "San Vicente Centenario",
    "lat": 14.89045,
    "lng": -88.28534
  },
  {
    "id": 3602287,
    "name": "San Francisco de Becerra",
    "lat": 14.63333,
    "lng": -86.1
  },
  {
    "id": 3601282,
    "name": "Sinuapa",
    "lat": 14.44305,
    "lng": -89.18594
  },
  {
    "id": 3606159,
    "name": "La Unión",
    "lat": 15.71667,
    "lng": -87.0
  },
  {
    "id": 3602205,
    "name": "San Jerónimo",
    "lat": 13.17667,
    "lng": -87.13639
  },
  {
    "id": 3600165,
    "name": "Yuscarán",
    "lat": 13.94439,
    "lng": -86.85241
  },
  {
    "id": 3608718,
    "name": "Jericó",
    "lat": 15.95,
    "lng": -85.96667
  },
  {
    "id": 3614797,
    "name": "Belén Gualcho",
    "lat": 14.48333,
    "lng": -88.8
  },
  {
    "id": 3604203,
    "name": "Orica",
    "lat": 14.7,
    "lng": -86.95
  },
  {
    "id": 3604292,
    "name": "Ojo de Agua",
    "lat": 14.01667,
    "lng": -86.35
  },
  {
    "id": 3602257,
    "name": "San Ignacio",
    "lat": 14.65,
    "lng": -87.03333
  },
  {
    "id": 3609415,
    "name": "Guaimitas",
    "lat": 15.5,
    "lng": -87.71667
  },
  {
    "id": 3600328,
    "name": "Villa Nueva",
    "lat": 14.03169,
    "lng": -87.14132
  },
  {
    "id": 3601566,
    "name": "Santa Lucía",
    "lat": 14.11568,
    "lng": -87.11368
  },
  {
    "id": 3610676,
    "name": "El Porvenir",
    "lat": 15.75,
    "lng": -86.93333
  },
  {
    "id": 3613175,
    "name": "Corozal",
    "lat": 15.8,
    "lng": -86.71667
  },
  {
    "id": 3603028,
    "name": "Quebrada Seca",
    "lat": 15.66065,
    "lng": -87.9493
  },
  {
    "id": 3604614,
    "name": "Monterrey",
    "lat": 15.58937,
    "lng": -87.88138
  },
  {
    "id": 3600605,
    "name": "Trinidad de Copán",
    "lat": 14.94567,
    "lng": -88.7422
  },
  {
    "id": 3601833,
    "name": "San Nicolás",
    "lat": 15.00341,
    "lng": -88.75167
  },
  {
    "id": 3614218,
    "name": "Cane",
    "lat": 14.27933,
    "lng": -87.65794
  },
  {
    "id": 3610051,
    "name": "El Triunfo de la Cruz",
    "lat": 15.76667,
    "lng": -87.43333
  },
  {
    "id": 3607003,
    "name": "La Sarrosa",
    "lat": 15.23333,
    "lng": -87.83333
  },
  {
    "id": 3610789,
    "name": "El Plan",
    "lat": 15.32641,
    "lng": -87.94984
  },
  {
    "id": 3600199,
    "name": "Yorito",
    "lat": 15.06667,
    "lng": -87.28333
  },
  {
    "id": 3614249,
    "name": "Cañaveral",
    "lat": 14.98401,
    "lng": -88.02486
  },
  {
    "id": 3615213,
    "name": "Amapala",
    "lat": 13.29222,
    "lng": -87.65389
  },
  {
    "id": 3607919,
    "name": "La Flecha",
    "lat": 15.29237,
    "lng": -88.48953
  },
  {
    "id": 3604389,
    "name": "Nueva Esperanza",
    "lat": 15.26667,
    "lng": -87.6
  },
  {
    "id": 3603256,
    "name": "Protección",
    "lat": 15.02764,
    "lng": -88.6469
  },
  {
    "id": 3604375,
    "name": "Nuevo Chamelecón",
    "lat": 15.38333,
    "lng": -88.01667
  },
  {
    "id": 3612810,
    "name": "Dulce Nombre de Culmí",
    "lat": 15.1,
    "lng": -85.53333
  },
  {
    "id": 3606035,
    "name": "Lepaterique",
    "lat": 14.06667,
    "lng": -87.46667
  },
  {
    "id": 3602680,
    "name": "Sabanagrande",
    "lat": 13.80778,
    "lng": -87.25917
  },
  {
    "id": 3602823,
    "name": "Río Abajo",
    "lat": 14.16927,
    "lng": -87.20515
  },
  {
    "id": 3610251,
    "name": "El Suyatal",
    "lat": 14.51667,
    "lng": -87.21667
  },
  {
    "id": 3607948,
    "name": "La Esperanza",
    "lat": 15.63333,
    "lng": -85.76667
  },
  {
    "id": 3613708,
    "name": "Chalmeca",
    "lat": 15.09579,
    "lng": -88.68036
  },
  {
    "id": 3600450,
    "name": "Vallecillo",
    "lat": 14.51667,
    "lng": -87.4
  },
  {
    "id": 3608142,
    "name": "La Concepción",
    "lat": 14.7,
    "lng": -86.23333
  },
  {
    "id": 3601936,
    "name": "San Luis",
    "lat": 14.74935,
    "lng": -87.40846
  },
  {
    "id": 3611267,
    "name": "El Mochito",
    "lat": 14.86667,
    "lng": -88.08333
  },
  {
    "id": 3602272,
    "name": "San Francisco de Yojoa",
    "lat": 15.01442,
    "lng": -87.9716
  },
  {
    "id": 3605000,
    "name": "Marcovia",
    "lat": 13.28806,
    "lng": -87.30972
  },
  {
    "id": 3610046,
    "name": "El Tular",
    "lat": 13.46639,
    "lng": -87.51528
  },
  {
    "id": 3611356,
    "name": "El Llano",
    "lat": 15.17939,
    "lng": -87.87952
  },
  {
    "id": 3611270,
    "name": "El Milagro",
    "lat": 15.4,
    "lng": -87.96667
  },
  {
    "id": 3611088,
    "name": "El Ocote",
    "lat": 15.41667,
    "lng": -86.56667
  },
  {
    "id": 3603130,
    "name": "Punuare",
    "lat": 14.73333,
    "lng": -85.96667
  },
  {
    "id": 3602118,
    "name": "San José",
    "lat": 15.31667,
    "lng": -87.16667
  },
  {
    "id": 3609775,
    "name": "Erandique",
    "lat": 14.23787,
    "lng": -88.46447
  },
  {
    "id": 3602277,
    "name": "San Francisco del Valle",
    "lat": 14.43542,
    "lng": -88.95608
  },
  {
    "id": 3601784,
    "name": "San Pedro de Tutule",
    "lat": 14.25145,
    "lng": -87.85414
  },
  {
    "id": 3615169,
    "name": "Antigua Ocotepeque",
    "lat": 14.40131,
    "lng": -89.19971
  },
  {
    "id": 3611319,
    "name": "El Marañón",
    "lat": 15.39518,
    "lng": -88.05437
  },
  {
    "id": 3601702,
    "name": "Santa Ana de Yusguare",
    "lat": 13.30056,
    "lng": -87.11389
  },
  {
    "id": 3615070,
    "name": "Arimís",
    "lat": 14.78333,
    "lng": -86.0
  },
  {
    "id": 3611718,
    "name": "El Guapinol",
    "lat": 13.76667,
    "lng": -87.46667
  },
  {
    "id": 3608860,
    "name": "Ilama",
    "lat": 15.06809,
    "lng": -88.22311
  },
  {
    "id": 3604503,
    "name": "Namasigüe",
    "lat": 13.20472,
    "lng": -87.13889
  },
  {
    "id": 3607436,
    "name": "Lamaní",
    "lat": 14.19626,
    "lng": -87.62128
  },
  {
    "id": 3602190,
    "name": "San Jerónimo",
    "lat": 14.62674,
    "lng": -87.60671
  },
  {
    "id": 3602092,
    "name": "San José",
    "lat": 14.90235,
    "lng": -88.72063
  },
  {
    "id": 3615030,
    "name": "Atenas de San Cristóbal",
    "lat": 15.68333,
    "lng": -87.31667
  },
  {
    "id": 3602546,
    "name": "San Agustín",
    "lat": 14.81958,
    "lng": -88.93562
  },
  {
    "id": 3615358,
    "name": "Agualote",
    "lat": 15.33621,
    "lng": -88.55312
  },
  {
    "id": 3612640,
    "name": "El Bálsamo",
    "lat": 15.06667,
    "lng": -87.46667
  },
  {
    "id": 3602602,
    "name": "Salamá",
    "lat": 15.75,
    "lng": -85.96667
  },
  {
    "id": 3608635,
    "name": "Jocón",
    "lat": 15.28333,
    "lng": -86.96667
  },
  {
    "id": 3615090,
    "name": "Arenal",
    "lat": 15.35,
    "lng": -86.83333
  },
  {
    "id": 3602474,
    "name": "San Antonio",
    "lat": 15.33333,
    "lng": -87.15
  },
  {
    "id": 3615028,
    "name": "Atima",
    "lat": 14.93253,
    "lng": -88.48965
  },
  {
    "id": 3611128,
    "name": "El Obraje",
    "lat": 14.0,
    "lng": -86.43333
  },
  {
    "id": 3609152,
    "name": "Guayape",
    "lat": 14.71667,
    "lng": -86.83333
  },
  {
    "id": 3604320,
    "name": "Ocote Paulino",
    "lat": 15.41667,
    "lng": -87.6
  },
  {
    "id": 3601518,
    "name": "Santa Rita",
    "lat": 14.91667,
    "lng": -88.21667
  },
  {
    "id": 3605436,
    "name": "Los Naranjos",
    "lat": 14.94398,
    "lng": -88.03654
  },
  {
    "id": 3612160,
    "name": "El Chichicaste",
    "lat": 14.06667,
    "lng": -86.3
  },
  {
    "id": 3607930,
    "name": "La Estancia",
    "lat": 15.28333,
    "lng": -87.55
  },
  {
    "id": 3604189,
    "name": "Orocuina",
    "lat": 13.48167,
    "lng": -87.105
  },
  {
    "id": 3610912,
    "name": "El Pedernal",
    "lat": 14.7,
    "lng": -87.11667
  },
  {
    "id": 3600895,
    "name": "Tepusteca",
    "lat": 15.41667,
    "lng": -86.31667
  },
  {
    "id": 3601993,
    "name": "San Juan de Opoa",
    "lat": 14.779,
    "lng": -88.69641
  },
  {
    "id": 3602065,
    "name": "San José de Tarros",
    "lat": 15.3,
    "lng": -88.7
  },
  {
    "id": 3612937,
    "name": "Cuyalí",
    "lat": 13.88333,
    "lng": -86.55
  },
  {
    "id": 3613509,
    "name": "Chotepe",
    "lat": 15.41667,
    "lng": -87.98333
  },
  {
    "id": 3614997,
    "name": "Ayapa",
    "lat": 15.11174,
    "lng": -87.17557
  },
  {
    "id": 3607053,
    "name": "La Rosa",
    "lat": 15.35,
    "lng": -87.06667
  },
  {
    "id": 3605837,
    "name": "Lomitas",
    "lat": 15.1,
    "lng": -87.21667
  },
  {
    "id": 3601367,
    "name": "Sensenti",
    "lat": 14.49379,
    "lng": -88.93761
  },
  {
    "id": 3607042,
    "name": "La Sabana",
    "lat": 15.37351,
    "lng": -87.93176
  },
  {
    "id": 3605018,
    "name": "Marale",
    "lat": 14.88333,
    "lng": -87.15
  },
  {
    "id": 3610487,
    "name": "El Rincón",
    "lat": 14.578,
    "lng": -87.92815
  },
  {
    "id": 3608828,
    "name": "Iralaya",
    "lat": 15.0,
    "lng": -83.23333
  },
  {
    "id": 3607931,
    "name": "La Estancia",
    "lat": 15.05,
    "lng": -86.35
  },
  {
    "id": 3615022,
    "name": "Auas",
    "lat": 15.48333,
    "lng": -84.33333
  },
  {
    "id": 3604712,
    "name": "Mojimán",
    "lat": 15.28094,
    "lng": -87.58652
  },
  {
    "id": 3615067,
    "name": "Armenia",
    "lat": 15.46667,
    "lng": -86.36667
  },
  {
    "id": 3610558,
    "name": "Rancho Grande",
    "lat": 14.68852,
    "lng": -87.49525
  },
  {
    "id": 3607992,
    "name": "La Encarnación",
    "lat": 14.66676,
    "lng": -89.08751
  },
  {
    "id": 3600280,
    "name": "Wawina",
    "lat": 15.41667,
    "lng": -84.43333
  },
  {
    "id": 3601733,
    "name": "San Sebastián",
    "lat": 14.24582,
    "lng": -87.63981
  },
  {
    "id": 3613286,
    "name": "Concepción de Guasistagua",
    "lat": 14.60764,
    "lng": -87.65499
  },
  {
    "id": 3614893,
    "name": "Bálsamo Oriental",
    "lat": 15.48333,
    "lng": -86.33333
  },
  {
    "id": 3602137,
    "name": "San José",
    "lat": 14.24809,
    "lng": -87.95951
  },
  {
    "id": 3607797,
    "name": "Laguna Verde",
    "lat": 15.2,
    "lng": -88.16667
  },
  {
    "id": 3605222,
    "name": "Lucerna",
    "lat": 14.55817,
    "lng": -88.9345
  },
  {
    "id": 3602396,
    "name": "San Buenaventura",
    "lat": 15.0243,
    "lng": -87.99447
  },
  {
    "id": 3600662,
    "name": "Tornabé",
    "lat": 15.75,
    "lng": -87.55
  },
  {
    "id": 3600271,
    "name": "Yaguacire",
    "lat": 14.01573,
    "lng": -87.216
  },
  {
    "id": 3607538,
    "name": "La Libertad",
    "lat": 14.81132,
    "lng": -88.58715
  },
  {
    "id": 3612949,
    "name": "Cusuna",
    "lat": 15.85,
    "lng": -85.23333
  },
  {
    "id": 3611352,
    "name": "El Lolo",
    "lat": 14.1345,
    "lng": -87.2545
  },
  {
    "id": 3610118,
    "name": "El Tigre",
    "lat": 14.93333,
    "lng": -87.98333
  },
  {
    "id": 3609342,
    "name": "Gualjoco",
    "lat": 14.9599,
    "lng": -88.23735
  },
  {
    "id": 3602077,
    "name": "San José del Boquerón",
    "lat": 15.51856,
    "lng": -87.89786
  },
  {
    "id": 3601664,
    "name": "Santa Cruz",
    "lat": 13.86667,
    "lng": -86.63333
  },
  {
    "id": 3605258,
    "name": "Los Tangos",
    "lat": 15.14585,
    "lng": -88.67931
  },
  {
    "id": 3607644,
    "name": "La Labor",
    "lat": 14.48625,
    "lng": -89.00272
  },
  {
    "id": 3604181,
    "name": "Oropolí",
    "lat": 13.81667,
    "lng": -86.81667
  },
  {
    "id": 3603035,
    "name": "Quebradas",
    "lat": 14.5,
    "lng": -87.35
  },
  {
    "id": 3602777,
    "name": "Río Chiquito",
    "lat": 15.63407,
    "lng": -88.24136
  },
  {
    "id": 3611699,
    "name": "El Guayabito",
    "lat": 14.83333,
    "lng": -86.03333
  },
  {
    "id": 3603137,
    "name": "Punta Ocote",
    "lat": 15.2,
    "lng": -87.28333
  },
  {
    "id": 3604395,
    "name": "Nueva Armenia",
    "lat": 15.79556,
    "lng": -86.49845
  },
  {
    "id": 3610318,
    "name": "El Sauce",
    "lat": 14.5285,
    "lng": -87.66571
  },
  {
    "id": 3603169,
    "name": "Puerto Alto",
    "lat": 15.7,
    "lng": -87.86667
  },
  {
    "id": 3608692,
    "name": "Jícaro Galán",
    "lat": 13.53167,
    "lng": -87.43889
  },
  {
    "id": 3601179,
    "name": "Subirana",
    "lat": 15.2,
    "lng": -87.45
  },
  {
    "id": 3601608,
    "name": "Santa Elena",
    "lat": 15.38333,
    "lng": -88.13333
  },
  {
    "id": 3609608,
    "name": "Goascorán",
    "lat": 13.58333,
    "lng": -87.61667
  },
  {
    "id": 3604263,
    "name": "Ojos de Agua",
    "lat": 14.7057,
    "lng": -88.81617
  },
  {
    "id": 3609742,
    "name": "Esquías",
    "lat": 14.74392,
    "lng": -87.3712
  },
  {
    "id": 3610687,
    "name": "El Porvenir",
    "lat": 14.58775,
    "lng": -87.89253
  },
  {
    "id": 3603343,
    "name": "Potrerillos",
    "lat": 14.55137,
    "lng": -87.8774
  },
  {
    "id": 3604184,
    "name": "Oropéndolas",
    "lat": 15.01667,
    "lng": -87.93333
  },
  {
    "id": 3609673,
    "name": "Francia",
    "lat": 15.85,
    "lng": -85.58333
  },
  {
    "id": 3602284,
    "name": "San Francisco de Coray",
    "lat": 13.66139,
    "lng": -87.53278
  },
  {
    "id": 3610610,
    "name": "El Puente",
    "lat": 13.28333,
    "lng": -87.11667
  },
  {
    "id": 3605382,
    "name": "Los Planes",
    "lat": 14.05,
    "lng": -88.01667
  },
  {
    "id": 3614343,
    "name": "Camalote",
    "lat": 15.33333,
    "lng": -88.33333
  },
  {
    "id": 3606097,
    "name": "La Virtud",
    "lat": 14.06137,
    "lng": -88.69482
  },
  {
    "id": 3606185,
    "name": "La Trinidad",
    "lat": 15.1,
    "lng": -87.2
  },
  {
    "id": 3601836,
    "name": "San Nicolás",
    "lat": 14.55,
    "lng": -86.25
  },
  {
    "id": 3606250,
    "name": "Las Vegas",
    "lat": 15.01667,
    "lng": -87.45
  },
  {
    "id": 3601951,
    "name": "San Lucas",
    "lat": 13.73333,
    "lng": -86.95
  },
  {
    "id": 3602368,
    "name": "San Diego",
    "lat": 14.05,
    "lng": -86.46667
  },
  {
    "id": 3601496,
    "name": "Santa Rosa de Aguán",
    "lat": 15.95,
    "lng": -85.71667
  },
  {
    "id": 3613402,
    "name": "Cofradía",
    "lat": 14.22399,
    "lng": -87.18014
  },
  {
    "id": 3609231,
    "name": "Guarizama",
    "lat": 14.91667,
    "lng": -86.33333
  },
  {
    "id": 3600057,
    "name": "Zopilotepe",
    "lat": 14.6,
    "lng": -86.26667
  },
  {
    "id": 3611933,
    "name": "El Cubolero",
    "lat": 13.46667,
    "lng": -87.66667
  },
  {
    "id": 3611481,
    "name": "El Juncal",
    "lat": 15.45,
    "lng": -86.43333
  },
  {
    "id": 3607146,
    "name": "La Playona",
    "lat": 15.11803,
    "lng": -88.98197
  },
  {
    "id": 3600626,
    "name": "Travesía",
    "lat": 15.86267,
    "lng": -87.90471
  },
  {
    "id": 3611040,
    "name": "El Olivar",
    "lat": 15.08333,
    "lng": -87.88333
  },
  {
    "id": 3614805,
    "name": "Bejuco",
    "lat": 15.13333,
    "lng": -87.93333
  },
  {
    "id": 3613263,
    "name": "Concordia",
    "lat": 14.61667,
    "lng": -86.65
  },
  {
    "id": 3600969,
    "name": "Taujica",
    "lat": 15.7,
    "lng": -85.91667
  },
  {
    "id": 3605053,
    "name": "Mangulile",
    "lat": 15.06667,
    "lng": -86.8
  },
  {
    "id": 3614975,
    "name": "Azacualpa",
    "lat": 14.71218,
    "lng": -88.0901
  },
  {
    "id": 3615011,
    "name": "Auka",
    "lat": 14.94087,
    "lng": -83.83229
  },
  {
    "id": 3601874,
    "name": "San Matías",
    "lat": 13.98333,
    "lng": -86.63333
  },
  {
    "id": 3609453,
    "name": "Guacamaya",
    "lat": 15.02044,
    "lng": -88.15025
  },
  {
    "id": 3604414,
    "name": "Nombre de Jesús",
    "lat": 15.35,
    "lng": -86.68333
  },
  {
    "id": 3608656,
    "name": "Jiquinlaca",
    "lat": 14.00595,
    "lng": -88.35162
  },
  {
    "id": 3603920,
    "name": "Paujiles",
    "lat": 15.1,
    "lng": -87.35
  },
  {
    "id": 3607838,
    "name": "La Guama",
    "lat": 14.88647,
    "lng": -87.93703
  },
  {
    "id": 3613900,
    "name": "Ceguaca",
    "lat": 14.80232,
    "lng": -88.20387
  },
  {
    "id": 3603998,
    "name": "Paptalaya",
    "lat": 15.5,
    "lng": -84.31667
  },
  {
    "id": 3601563,
    "name": "Santa Lucía",
    "lat": 14.41667,
    "lng": -89.2
  },
  {
    "id": 3611719,
    "name": "El Guantillo",
    "lat": 14.6,
    "lng": -87.3
  },
  {
    "id": 3603167,
    "name": "Puerto Castilla",
    "lat": 16.01667,
    "lng": -85.96667
  },
  {
    "id": 3607830,
    "name": "La Guata",
    "lat": 15.08333,
    "lng": -86.38333
  },
  {
    "id": 3603041,
    "name": "Quebrada Larga",
    "lat": 14.1,
    "lng": -86.36667
  },
  {
    "id": 3612784,
    "name": "El Achiotal",
    "lat": 14.08333,
    "lng": -88.75
  },
  {
    "id": 3602769,
    "name": "Río Esteban",
    "lat": 15.83333,
    "lng": -86.3
  },
  {
    "id": 3608631,
    "name": "Joconal",
    "lat": 15.35519,
    "lng": -88.63295
  },
  {
    "id": 3611987,
    "name": "Corpus",
    "lat": 13.28889,
    "lng": -87.03472
  },
  {
    "id": 3611986,
    "name": "El Corpús",
    "lat": 14.69814,
    "lng": -88.90862
  },
  {
    "id": 3603136,
    "name": "Punta Piedra",
    "lat": 15.9,
    "lng": -85.28333
  },
  {
    "id": 3600254,
    "name": "Yamaranguila",
    "lat": 14.28333,
    "lng": -88.24199
  },
  {
    "id": 3611844,
    "name": "El Escanito",
    "lat": 14.66667,
    "lng": -87.1
  },
  {
    "id": 3601672,
    "name": "Santa Cruz",
    "lat": 13.25806,
    "lng": -87.34833
  },
  {
    "id": 3611133,
    "name": "El Obraje",
    "lat": 13.15417,
    "lng": -87.13083
  },
  {
    "id": 3613847,
    "name": "Cerro Blanco",
    "lat": 14.66321,
    "lng": -87.78535
  },
  {
    "id": 3612801,
    "name": "Duyure",
    "lat": 13.63333,
    "lng": -86.81667
  },
  {
    "id": 3613145,
    "name": "Correderos",
    "lat": 15.41778,
    "lng": -88.4552
  },
  {
    "id": 3615108,
    "name": "Araulí",
    "lat": 13.973,
    "lng": -86.545
  },
  {
    "id": 3608522,
    "name": "Jutiapa",
    "lat": 13.98333,
    "lng": -86.4
  },
  {
    "id": 3604949,
    "name": "Mata de Plátano",
    "lat": 14.6,
    "lng": -87.28333
  },
  {
    "id": 3602473,
    "name": "San Antonio",
    "lat": 15.6,
    "lng": -87.15
  },
  {
    "id": 3614328,
    "name": "Camasca",
    "lat": 13.99677,
    "lng": -88.37973
  },
  {
    "id": 3605729,
    "name": "Los Caminos",
    "lat": 14.95045,
    "lng": -87.97531
  },
  {
    "id": 3604265,
    "name": "Ojos de Agua",
    "lat": 14.6,
    "lng": -87.93333
  },
  {
    "id": 3612138,
    "name": "El Chimbo",
    "lat": 14.13575,
    "lng": -87.11879
  },
  {
    "id": 3613105,
    "name": "Coyoles Central",
    "lat": 15.4,
    "lng": -86.66667
  },
  {
    "id": 3610866,
    "name": "El Perico",
    "lat": 15.08333,
    "lng": -88.1
  },
  {
    "id": 3606319,
    "name": "Las Tejeras",
    "lat": 14.80442,
    "lng": -88.59508
  },
  {
    "id": 3607731,
    "name": "La Bueso",
    "lat": 15.61689,
    "lng": -87.85688
  },
  {
    "id": 3614583,
    "name": "Buenos Aires",
    "lat": 15.03333,
    "lng": -88.96667
  },
  {
    "id": 3607802,
    "name": "Laguna Seca",
    "lat": 14.7,
    "lng": -86.1
  },
  {
    "id": 3602169,
    "name": "San Joaquín",
    "lat": 15.06053,
    "lng": -88.91193
  },
  {
    "id": 3610232,
    "name": "El Tablón",
    "lat": 14.03333,
    "lng": -87.16667
  },
  {
    "id": 3607030,
    "name": "Las Ánimas",
    "lat": 14.25,
    "lng": -86.56667
  },
  {
    "id": 3600951,
    "name": "Teguajinal",
    "lat": 15.36667,
    "lng": -86.6
  },
  {
    "id": 3602984,
    "name": "Quezailica",
    "lat": 14.87652,
    "lng": -88.72714
  },
  {
    "id": 3601302,
    "name": "Silca",
    "lat": 14.83333,
    "lng": -86.53333
  },
  {
    "id": 3601925,
    "name": "San Luis de Planes",
    "lat": 14.97603,
    "lng": -88.1251
  },
  {
    "id": 3612838,
    "name": "Dolores",
    "lat": 14.87459,
    "lng": -88.81637
  },
  {
    "id": 3608743,
    "name": "Jamalteca",
    "lat": 14.69597,
    "lng": -87.57908
  },
  {
    "id": 3600236,
    "name": "Yaruchel",
    "lat": 14.52794,
    "lng": -88.81579
  },
  {
    "id": 3615332,
    "name": "Aguas del Padre",
    "lat": 14.58081,
    "lng": -87.87865
  },
  {
    "id": 3603267,
    "name": "Prieta",
    "lat": 15.5806,
    "lng": -86.13664
  },
  {
    "id": 3614113,
    "name": "Carbajales",
    "lat": 15.51667,
    "lng": -86.35
  },
  {
    "id": 3603326,
    "name": "Potrerillos",
    "lat": 15.63333,
    "lng": -88.3
  },
  {
    "id": 3612581,
    "name": "El Benque",
    "lat": 14.03333,
    "lng": -86.46667
  },
  {
    "id": 3610555,
    "name": "El Rancho",
    "lat": 15.66667,
    "lng": -87.95
  },
  {
    "id": 3600421,
    "name": "Valle de Ángeles",
    "lat": 14.49921,
    "lng": -87.63989
  },
  {
    "id": 3605042,
    "name": "Manto",
    "lat": 14.91667,
    "lng": -86.38333
  },
  {
    "id": 3604386,
    "name": "Nueva Jalapa",
    "lat": 14.91667,
    "lng": -88.33333
  },
  {
    "id": 3602852,
    "name": "Reitoca",
    "lat": 13.82583,
    "lng": -87.46528
  },
  {
    "id": 3613805,
    "name": "Cerro Grande",
    "lat": 13.81667,
    "lng": -87.25
  },
  {
    "id": 3610278,
    "name": "El Socorro",
    "lat": 14.62708,
    "lng": -87.90527
  },
  {
    "id": 3602070,
    "name": "San José del Potrero",
    "lat": 14.83999,
    "lng": -87.28405
  },
  {
    "id": 3610139,
    "name": "El Terrero",
    "lat": 14.06366,
    "lng": -87.06602
  },
  {
    "id": 3606075,
    "name": "La Zumbadora",
    "lat": 15.01433,
    "lng": -88.90117
  },
  {
    "id": 3606901,
    "name": "San José de Las Conchas",
    "lat": 13.32528,
    "lng": -87.39556
  },
  {
    "id": 3611720,
    "name": "El Guante",
    "lat": 14.55,
    "lng": -87.1
  },
  {
    "id": 3615557,
    "name": "Agua Azul",
    "lat": 14.91667,
    "lng": -87.96667
  },
  {
    "id": 3615473,
    "name": "Agua Caliente",
    "lat": 14.88333,
    "lng": -88.81667
  },
  {
    "id": 3602359,
    "name": "Sandy Bay",
    "lat": 16.32923,
    "lng": -86.56446
  },
  {
    "id": 3615115,
    "name": "Aramecina",
    "lat": 13.74222,
    "lng": -87.71028
  },
  {
    "id": 3602066,
    "name": "San José de Río Tinto",
    "lat": 14.93333,
    "lng": -85.7
  },
  {
    "id": 3600598,
    "name": "Trojas",
    "lat": 15.35,
    "lng": -86.7
  },
  {
    "id": 3605873,
    "name": "Loma Alta",
    "lat": 15.39818,
    "lng": -88.56251
  },
  {
    "id": 3603799,
    "name": "Petoa",
    "lat": 15.26939,
    "lng": -88.28878
  },
  {
    "id": 3602286,
    "name": "San Francisco de Cones",
    "lat": 14.51667,
    "lng": -88.9
  },
  {
    "id": 3602094,
    "name": "San José de Comayagua",
    "lat": 14.73333,
    "lng": -88.03333
  },
  {
    "id": 3601780,
    "name": "San Pedro Zacapa",
    "lat": 14.7565,
    "lng": -88.11373
  },
  {
    "id": 3614914,
    "name": "Baja Mar",
    "lat": 15.88851,
    "lng": -87.85547
  },
  {
    "id": 3605060,
    "name": "Mangrove Bight",
    "lat": 16.46667,
    "lng": -85.88333
  },
  {
    "id": 3608377,
    "name": "La Brea",
    "lat": 15.8,
    "lng": -85.96667
  },
  {
    "id": 3602785,
    "name": "Río Bonito",
    "lat": 14.76667,
    "lng": -87.88333
  },
  {
    "id": 3603224,
    "name": "Pueblo Nuevo",
    "lat": 15.0,
    "lng": -88.75
  },
  {
    "id": 3601719,
    "name": "Santa Ana",
    "lat": 13.93167,
    "lng": -87.27139
  },
  {
    "id": 3614789,
    "name": "Berlín",
    "lat": 14.84281,
    "lng": -88.49452
  },
  {
    "id": 3613281,
    "name": "Concepción del Sur",
    "lat": 14.8,
    "lng": -88.16667
  },
  {
    "id": 3601992,
    "name": "San Juan de Planes",
    "lat": 14.93333,
    "lng": -88.78333
  },
  {
    "id": 3602184,
    "name": "San Jerónimo",
    "lat": 14.96667,
    "lng": -88.86667
  },
  {
    "id": 3600382,
    "name": "Veracruz",
    "lat": 14.91667,
    "lng": -88.78333
  },
  {
    "id": 3615556,
    "name": "Agua Azul Rancho",
    "lat": 14.9,
    "lng": -87.95
  },
  {
    "id": 3600997,
    "name": "Taragual",
    "lat": 14.75,
    "lng": -88.48333
  },
  {
    "id": 3613906,
    "name": "Cedros",
    "lat": 14.6,
    "lng": -87.11667
  },
  {
    "id": 3605491,
    "name": "Los Llanitos",
    "lat": 13.28694,
    "lng": -87.33444
  },
  {
    "id": 3600906,
    "name": "Tepanguare",
    "lat": 14.33333,
    "lng": -87.75
  },
  {
    "id": 3611995,
    "name": "El Corozal",
    "lat": 15.06667,
    "lng": -88.61667
  },
  {
    "id": 3611069,
    "name": "El Ocotón",
    "lat": 15.03333,
    "lng": -88.88333
  },
  {
    "id": 3614381,
    "name": "Callejones",
    "lat": 15.16667,
    "lng": -88.65
  },
  {
    "id": 3602436,
    "name": "San Antonio de la Cuesta",
    "lat": 14.64299,
    "lng": -87.60232
  },
  {
    "id": 3601402,
    "name": "Savannah Bight",
    "lat": 16.48458,
    "lng": -85.84474
  },
  {
    "id": 3614011,
    "name": "Casa Quemada",
    "lat": 15.26667,
    "lng": -88.55
  },
  {
    "id": 3615582,
    "name": "Agalteca",
    "lat": 14.45,
    "lng": -87.26667
  },
  {
    "id": 3611842,
    "name": "El Escaño de Tepale",
    "lat": 14.75,
    "lng": -87.06667
  },
  {
    "id": 3602337,
    "name": "San Fernando",
    "lat": 14.68333,
    "lng": -89.11667
  },
  {
    "id": 3610082,
    "name": "El Tránsito",
    "lat": 14.38333,
    "lng": -88.91667
  },
  {
    "id": 3605950,
    "name": "Liure",
    "lat": 13.53583,
    "lng": -87.09194
  },
  {
    "id": 3604911,
    "name": "Mateo",
    "lat": 14.07731,
    "lng": -87.3169
  },
  {
    "id": 3613547,
    "name": "Chivana",
    "lat": 15.75,
    "lng": -87.98333
  },
  {
    "id": 3612734,
    "name": "El Agua Dulcita",
    "lat": 14.7,
    "lng": -87.75
  },
  {
    "id": 3610365,
    "name": "El Rusio",
    "lat": 14.46667,
    "lng": -86.36667
  },
  {
    "id": 3613371,
    "name": "Cololaca",
    "lat": 14.3,
    "lng": -88.88333
  },
  {
    "id": 3613285,
    "name": "Concepción de la Barranca",
    "lat": 15.16667,
    "lng": -88.71667
  },
  {
    "id": 3812188,
    "name": "Texíguat",
    "lat": 13.64972,
    "lng": -87.0225
  },
  {
    "id": 3602428,
    "name": "San Antonio del Norte",
    "lat": 13.88444,
    "lng": -87.70306
  },
  {
    "id": 3608112,
    "name": "La Criba",
    "lat": 13.45361,
    "lng": -87.41333
  },
  {
    "id": 3606549,
    "name": "Las Mercedes",
    "lat": 14.28333,
    "lng": -87.56667
  },
  {
    "id": 3602813,
    "name": "Río Amarillo",
    "lat": 14.96667,
    "lng": -89.13333
  },
  {
    "id": 3603696,
    "name": "Piedras Amarillas",
    "lat": 15.68333,
    "lng": -86.56667
  },
  {
    "id": 3605203,
    "name": "Macholoa",
    "lat": 14.91667,
    "lng": -88.3
  },
  {
    "id": 3607810,
    "name": "Lagunas",
    "lat": 14.61667,
    "lng": -88.48333
  },
  {
    "id": 3607950,
    "name": "La Esperanza",
    "lat": 15.41667,
    "lng": -88.18333
  },
  {
    "id": 3604855,
    "name": "Mercedes",
    "lat": 14.43333,
    "lng": -89.15
  },
  {
    "id": 3615226,
    "name": "Alubarén",
    "lat": 13.79611,
    "lng": -87.46889
  },
  {
    "id": 3613586,
    "name": "Chiquila",
    "lat": 15.23333,
    "lng": -88.58333
  },
  {
    "id": 3608022,
    "name": "La Curva",
    "lat": 15.8,
    "lng": -85.76667
  },
  {
    "id": 3614574,
    "name": "Buenos Aires",
    "lat": 15.46667,
    "lng": -86.4
  },
  {
    "id": 3614572,
    "name": "Buenos Aires",
    "lat": 15.48333,
    "lng": -88.18333
  },
  {
    "id": 3608155,
    "name": "La Colorada",
    "lat": 15.61667,
    "lng": -86.81667
  },
  {
    "id": 3601835,
    "name": "San Nicolás",
    "lat": 14.71667,
    "lng": -87.35
  },
  {
    "id": 3615439,
    "name": "Agua Caliente de Linaca",
    "lat": 13.43528,
    "lng": -87.23167
  },
  {
    "id": 3604576,
    "name": "Morolica",
    "lat": 13.56667,
    "lng": -86.9
  },
  {
    "id": 3607679,
    "name": "La Jigua",
    "lat": 15.03333,
    "lng": -88.8
  },
  {
    "id": 3609884,
    "name": "El Zapote",
    "lat": 15.01667,
    "lng": -87.85
  },
  {
    "id": 3600301,
    "name": "Waksma",
    "lat": 15.43333,
    "lng": -84.4
  },
  {
    "id": 3614983,
    "name": "Azacualpa",
    "lat": 14.26667,
    "lng": -88.38333
  },
  {
    "id": 3605179,
    "name": "Magdalena",
    "lat": 13.86667,
    "lng": -88.3
  },
  {
    "id": 3610375,
    "name": "El Rosario",
    "lat": 14.9,
    "lng": -86.68333
  },
  {
    "id": 3602488,
    "name": "San Antonio",
    "lat": 14.51667,
    "lng": -88.96667
  },
  {
    "id": 3610710,
    "name": "El Portillo de González",
    "lat": 15.28333,
    "lng": -87.6
  },
  {
    "id": 3603232,
    "name": "Pueblo Nuevo",
    "lat": 14.38333,
    "lng": -87.28333
  },
  {
    "id": 3602068,
    "name": "San José de Pane",
    "lat": 14.48333,
    "lng": -87.83333
  },
  {
    "id": 3610867,
    "name": "El Perico",
    "lat": 13.13889,
    "lng": -87.03222
  },
  {
    "id": 3613191,
    "name": "Corinto",
    "lat": 15.58333,
    "lng": -88.36667
  },
  {
    "id": 3611881,
    "name": "El Edén",
    "lat": 14.95,
    "lng": -88.01667
  },
  {
    "id": 3607079,
    "name": "La Reina",
    "lat": 15.11667,
    "lng": -88.63333
  },
  {
    "id": 3608728,
    "name": "Jardines",
    "lat": 14.7,
    "lng": -87.98333
  },
  {
    "id": 3609191,
    "name": "Guatemalita",
    "lat": 14.11667,
    "lng": -88.61667
  },
  {
    "id": 3604376,
    "name": "Nuevo Celilac",
    "lat": 14.98333,
    "lng": -88.33333
  },
  {
    "id": 3613108,
    "name": "Coyoles",
    "lat": 15.46667,
    "lng": -86.68333
  },
  {
    "id": 3600313,
    "name": "Vivistorio",
    "lat": 14.9,
    "lng": -88.73333
  },
  {
    "id": 3611847,
    "name": "El Ermitano",
    "lat": 15.25,
    "lng": -88.68333
  },
  {
    "id": 3613283,
    "name": "Concepción del Norte",
    "lat": 15.16667,
    "lng": -88.13333
  },
  {
    "id": 3612554,
    "name": "El Buen Pastor",
    "lat": 14.86667,
    "lng": -87.78333
  },
  {
    "id": 3604922,
    "name": "Matarras",
    "lat": 15.51667,
    "lng": -87.4
  },
  {
    "id": 3605082,
    "name": "Mandasta",
    "lat": 13.73333,
    "lng": -86.91667
  },
  {
    "id": 3604387,
    "name": "Nueva Granada",
    "lat": 15.11667,
    "lng": -88.1
  },
  {
    "id": 3602549,
    "name": "San Agustín",
    "lat": 13.2,
    "lng": -87.11667
  },
  {
    "id": 3607996,
    "name": "La Empalizada",
    "lat": 14.65,
    "lng": -86.13333
  },
  {
    "id": 3611914,
    "name": "El Derrumbo",
    "lat": 14.75,
    "lng": -88.78333
  },
  {
    "id": 3600754,
    "name": "Tikiraya",
    "lat": 15.01667,
    "lng": -83.63333
  },
  {
    "id": 3613279,
    "name": "Concepción de María",
    "lat": 13.21667,
    "lng": -87.0
  },
  {
    "id": 3611887,
    "name": "El Durazno",
    "lat": 14.137,
    "lng": -87.26407
  },
  {
    "id": 3613552,
    "name": "Chirinos",
    "lat": 15.4,
    "lng": -86.58333
  },
  {
    "id": 3607957,
    "name": "La Esperanza",
    "lat": 15.05091,
    "lng": -89.09818
  },
  {
    "id": 3604836,
    "name": "Mezapa",
    "lat": 15.55,
    "lng": -87.38333
  },
  {
    "id": 3605758,
    "name": "Los Arroyos",
    "lat": 14.65,
    "lng": -88.88333
  },
  {
    "id": 3601596,
    "name": "Santa Fe",
    "lat": 14.51667,
    "lng": -89.23333
  },
  {
    "id": 3601479,
    "name": "Santa Teresa",
    "lat": 14.38333,
    "lng": -89.0
  },
  {
    "id": 3605907,
    "name": "Llano Largo",
    "lat": 14.46667,
    "lng": -89.01667
  },
  {
    "id": 3610860,
    "name": "El Pescadero",
    "lat": 13.93333,
    "lng": -86.55
  },
  {
    "id": 3604089,
    "name": "Palkaka",
    "lat": 15.31667,
    "lng": -83.86667
  },
  {
    "id": 3604047,
    "name": "Palo Pintado",
    "lat": 14.51667,
    "lng": -87.68333
  },
  {
    "id": 3604388,
    "name": "Nueva Florida",
    "lat": 15.46667,
    "lng": -87.5
  },
  {
    "id": 3609027,
    "name": "Hicaque",
    "lat": 15.71667,
    "lng": -87.36667
  },
  {
    "id": 3604894,
    "name": "Meámbar",
    "lat": 14.78333,
    "lng": -87.76667
  },
  {
    "id": 3603329,
    "name": "Potrerillos",
    "lat": 15.26667,
    "lng": -88.43333
  },
  {
    "id": 3607905,
    "name": "La Florida",
    "lat": 14.06667,
    "lng": -87.98333
  },
  {
    "id": 3603084,
    "name": "Quebrada de Yoro",
    "lat": 15.43333,
    "lng": -87.78333
  },
  {
    "id": 3602008,
    "name": "San Juancito",
    "lat": 14.2195,
    "lng": -87.0656
  },
  {
    "id": 3610412,
    "name": "El Rodeo",
    "lat": 14.28333,
    "lng": -86.6
  },
  {
    "id": 3611697,
    "name": "El Guayabo",
    "lat": 13.48944,
    "lng": -87.44389
  },
  {
    "id": 3607565,
    "name": "La Laguna del Pedernal",
    "lat": 14.81667,
    "lng": -88.56667
  },
  {
    "id": 3602069,
    "name": "San José de Oriente",
    "lat": 15.03333,
    "lng": -88.11667
  },
  {
    "id": 3602690,
    "name": "Sabana Abajo",
    "lat": 14.6,
    "lng": -86.58333
  },
  {
    "id": 3602330,
    "name": "San Francisco",
    "lat": 13.36667,
    "lng": -86.9
  },
  {
    "id": 3606187,
    "name": "La Trinidad",
    "lat": 14.71667,
    "lng": -87.66667
  },
  {
    "id": 3611759,
    "name": "El Granzal",
    "lat": 14.4,
    "lng": -88.86667
  },
  {
    "id": 3604396,
    "name": "Nueva Armenia",
    "lat": 15.03333,
    "lng": -89.1
  },
  {
    "id": 3601651,
    "name": "Santa Cruz",
    "lat": 14.75,
    "lng": -88.98333
  },
  {
    "id": 3604172,
    "name": "Ostumán",
    "lat": 14.83333,
    "lng": -89.16667
  },
  {
    "id": 3602275,
    "name": "San Francisco de Ojuera",
    "lat": 14.75,
    "lng": -88.18333
  },
  {
    "id": 3601626,
    "name": "Santa Cruz Minas",
    "lat": 15.36667,
    "lng": -88.3
  },
  {
    "id": 3606164,
    "name": "La Unión",
    "lat": 15.13333,
    "lng": -88.55
  },
  {
    "id": 3606320,
    "name": "Las Tapias",
    "lat": 14.0672,
    "lng": -87.28212
  },
  {
    "id": 9072478,
    "name": "La Ruidosa",
    "lat": 15.23628,
    "lng": -88.75142
  },
  {
    "id": 3600491,
    "name": "Urrutia",
    "lat": 14.75,
    "lng": -87.03333
  },
  {
    "id": 3610092,
    "name": "El Tizatillo",
    "lat": 14.00183,
    "lng": -87.19768
  }
]