[
  {
    "id": 3489854,
    "name": "Kingston",
    "lat": 17.99702,
    "lng": -76.79358
  },
  {
    "id": 3488465,
    "name": "Spanish Town",
    "lat": 17.99107,
    "lng": -76.95742
  },
  {
    "id": 3488981,
    "name": "Portmore",
    "lat": 17.97102,
    "lng": -76.88691
  },
  {
    "id": 3489460,
    "name": "Montego Bay",
    "lat": 18.47116,
    "lng": -77.91883
  },
  {
    "id": 3489577,
    "name": "Mandeville",
    "lat": 18.04168,
    "lng": -77.50714
  },
  {
    "id": 3489523,
    "name": "May Pen",
    "lat": 17.96454,
    "lng": -77.24515
  },
  {
    "id": 3489227,
    "name": "Old Harbour",
    "lat": 17.94144,
    "lng": -77.10898
  },
  {
    "id": 3489760,
    "name": "Linstead",
    "lat": 18.13683,
    "lng": -77.03171
  },
  {
    "id": 3490165,
    "name": "Half Way Tree",
    "lat": 18.01248,
    "lng": -76.79928
  },
  {
    "id": 3488613,
    "name": "Savanna-la-Mar",
    "lat": 18.21895,
    "lng": -78.1332
  }
]